tool2openai/__init__.py
tool2openai/tool2openai.py
tool2openai-0.1.6.dist-info/licenses/LICENSE
tool2openai-0.1.6.dist-info/METADATA
tool2openai-0.1.6.dist-info/WHEEL
tool2openai-0.1.6.dist-info/top_level.txt
tool2openai-0.1.6.dist-info/RECORD
