Metadata-Version: 2.4
Name: tool2openai
Version: 0.1.6
Summary: Набор простеньких инструментов для собственного openai-совместимого эндпоинта.
Home-page: https://github.com/nehc/tool2openai
Author: Nehcy
Author-email: cibershaman@пmail.com
License-Expression: MIT
Requires-Python: >=3.10
License-File: LICENSE
Requires-Dist: openai>=1.98.0
Dynamic: author
Dynamic: author-email
Dynamic: home-page
Dynamic: license-file
Dynamic: requires-python
